pytexalarm/__init__.py
pytexalarm/decode.py
pytexalarm/hexdump.py
pytexalarm/pialarm.py
pytexalarm/py.typed
pytexalarm/trace_pcap.py
pytexalarm/trace_uart.py
pytexalarm/udl.py
pytexalarm/udlclient.py
pytexalarm/udlserver.py
pytexalarm/webapp.py
pytexalarm/static/dashboard.js
pytexalarm/templates/config.jinja2
pytexalarm/templates/json.jinja2
pytexalarm/templates/memory.jinja2
pytexalarm/templates/template.jinja2
pytexalarm/templates/user-detail.jinja2
pytexalarm-0.1a2.dist-info/licenses/LICENSE
pytexalarm-0.1a2.dist-info/METADATA
pytexalarm-0.1a2.dist-info/WHEEL
pytexalarm-0.1a2.dist-info/top_level.txt
pytexalarm-0.1a2.dist-info/RECORD
