Metadata-Version: 2.4
Name: pytexalarm
Version: 0.1a2
Summary: Interface with Texecom Alarm panels over UDL protocol in python
Author-email: Chris Shucksmith <chris@shucksmith.co.uk>
License-Expression: MIT
Project-URL: Homepage, https://github.com/shuckc/pytexalarm
Project-URL: Issues, https://github.com/shuckc/pytexalarm/issues
Classifier: Programming Language :: Python :: 3.9
Classifier: Programming Language :: Python :: 3.10
Classifier: Programming Language :: Python :: 3.11
Classifier: Programming Language :: Python :: 3.12
Classifier: Programming Language :: Python :: 3.13
Classifier: Operating System :: OS Independent
Requires-Python: >=3.9
License-File: LICENSE
Requires-Dist: prompt_toolkit>=3.0.0
Requires-Dist: aiohttp-jinja2>=1.6.0
Requires-Dist: pyserial_asyncio_fast>=0.16
Dynamic: license-file
